Metadata-Version: 2.1
Name: prodpad
Version: 0.1
Summary: This library makes it easier to interact with the Prodpad API in python scripts
Home-page: https://github.com/cmcgovern/prodpad
Author: Colin McGovern
Author-email: colin.mcgovern@gmail.com
License: UNKNOWN
Platform: UNKNOWN
Classifier: Operating System :: POSIX :: Linux
Classifier: License :: OSI Approved :: MIT License
Classifier: Programming Language :: Python :: 3.5
Classifier: Programming Language :: Python :: 3.6
Classifier: Programming Language :: Python :: 3.7
